<?xml version="1.0" encoding="UTF-8"?>
<Configuration>
  <Handlers>
    <Console name="consoleHandler">
      <PatternLayout pattern="%d{HH:mm:ss.SSS}::%N [%t] %level %logger{36} - %msg%n"/>
    </Console>
    <File name="fileHandler" fileName="resources/logs/app-logs.txt">
      <PatternLayout pattern="to file: %d{HH:mm:ss.SSS}::%N [%t] %level %logger{36} - %msg"/>
    </File>
    <Mail name="mailHandler">
      <PatternLayout pattern="to mail: %d{HH:mm:ss.SSS}::%N [%t] %level %logger{36} - %msg%n"/>
      <Properties>
        <Property name="mail.smtp.auth" value="true"/>
        <Property name="mail.smtp.starttls.enable" value="true"/>
        <Property name="mail.smtp.host" value="smtp.mailtrap.io"/>
        <Property name="mail.smtp.port" value="2525"/>
        <Property name="mail.smtp.ssl.trust" value="smtp.mailtrap.io"/>
        <Property name="mail.smtp.user" value="9037aa6f74e463"/>
        <Property name="mail.smtp.password" value="f9ae46d93c0655"/>
        <Property name="mail.smtp.from" value="nclogger@mail.ru"/>
        <Property name="mail.smtp.to" value="prodanovmd@gmail.com"/>
        <Property name="mail.smtp.subject" value="My Application Logs"/>
      </Properties>
    </Mail>
    <HTML name="htmlHandler" fileName="resources/logs/app-logs.html">
      <HTMLLayout title="My title" dateTimePattern="HH:mm:ss.SSS"/>
    </HTML>
  </Handlers>
  <Filters>
    <Level name="errorLevelFilter" level="error" mode="equal"/>
    <Level name="infoLevelFilter" level="info" mode="equal"/>
  </Filters>
  <Loggers>
    <Logger name="com.netcracker.project.MyClass" filtersMode="or">
      <HandlerRef ref="consoleHandler"/>
      <HandlerRef ref="fileHandler"/>
      <HandlerRef ref="mailHandler"/>
      <HandlerRef ref="htmlHandler"/>
      <FilterRef ref="errorLevelFilter"/>
      <FilterRef ref="infoLevelFilter"/>
    </Logger>
  </Loggers>
</Configuration>